README.txt
setup.py
collective/__init__.py
collective.pfg.creditcardfields.egg-info/PKG-INFO
collective.pfg.creditcardfields.egg-info/SOURCES.txt
collective.pfg.creditcardfields.egg-info/dependency_links.txt
collective.pfg.creditcardfields.egg-info/entry_points.txt
collective.pfg.creditcardfields.egg-info/namespace_packages.txt
collective.pfg.creditcardfields.egg-info/not-zip-safe
collective.pfg.creditcardfields.egg-info/requires.txt
collective.pfg.creditcardfields.egg-info/top_level.txt
collective/pfg/__init__.py
collective/pfg/creditcardfields/__init__.py
collective/pfg/creditcardfields/config.py
collective/pfg/creditcardfields/configure.zcml
collective/pfg/creditcardfields/fields.py
collective/pfg/creditcardfields/interfaces.py
collective/pfg/creditcardfields/profiles/default/factorytool.xml
collective/pfg/creditcardfields/profiles/default/rolemap.xml
collective/pfg/creditcardfields/profiles/default/skins.xml
collective/pfg/creditcardfields/profiles/default/types.xml
collective/pfg/creditcardfields/profiles/default/workflows.xml
collective/pfg/creditcardfields/profiles/default/types/FieldsetFolder.xml
collective/pfg/creditcardfields/profiles/default/types/FormExpirationDateField.xml
collective/pfg/creditcardfields/profiles/default/types/FormFolder.xml
collective/pfg/creditcardfields/skins/pfg_creditcardfields/expirationdatecalendar.pt
docs/HISTORY.txt