Metadata-Version: 1.0
Name: collective.pfg.creditcardfields
Version: 1.3
Summary: PFG extension, to be able to use fields specific to credit cards
Home-page: http://sixfeetup.com
Author: Lucie Lejard
Author-email: lucie@sixfeetup.com
License: GPL
Platform: UNKNOWN
Classifier: Programming Language :: Python
Classifier: Topic :: Software Development :: Libraries :: Python Modules
